BrowserAutomationLauncher/__init__.py
BrowserAutomationLauncher/_browser.py
BrowserAutomationLauncher/launcher.py
BrowserAutomationLauncher/_utils/data_packet.py
BrowserAutomationLauncher/_utils/tools/__init__.py
BrowserAutomationLauncher/_utils/tools/_common.py
BrowserAutomationLauncher/_utils/tools/_date_time.py
BrowserAutomationLauncher/_utils/tools/_dict.py
BrowserAutomationLauncher/_utils/tools/_downloader.py
BrowserAutomationLauncher/_utils/tools/_os.py
BrowserAutomationLauncher/_utils/tools/_web.py
browser_automation_launcher-2.0.3.dist-info/METADATA
browser_automation_launcher-2.0.3.dist-info/WHEEL
browser_automation_launcher-2.0.3.dist-info/licenses/LICENSE
browser_automation_launcher-2.0.3.dist-info/RECORD
