Metadata-Version: 2.4
Name: browser-automation-launcher
Version: 2.0.3
Summary: Browser Automation launcher
Author: Martian Bugs
License-File: LICENSE
Requires-Python: >=3.12
Requires-Dist: drissionpage<5.0.0.0,>=4.1.1.2
